furiosa/models/__init__.py
furiosa/models/_utils.py
furiosa/models/errors.py
furiosa/models/types.py
furiosa/models/cli/__init__.py
furiosa/models/cli/api.py
furiosa/models/cli/main.py
furiosa/models/data/.gitignore
furiosa/models/data/README.md
furiosa/models/data/enf_generator.py
furiosa/models/data/requirements.txt
furiosa/models/data/efficientnet_b0/efficientnet_b0.calib_range.yaml.dvc
furiosa/models/data/efficientnet_b0/efficientnet_b0_f32.onnx.dvc
furiosa/models/data/efficientnet_v2_s/efficientnet_v2_s.calib_range.yaml.dvc
furiosa/models/data/efficientnet_v2_s/efficientnet_v2_s_f32.onnx.dvc
furiosa/models/data/generated/0.10.0_f8f05c8ea/efficientnet_b0_warboy_1pe.enf.dvc
furiosa/models/data/generated/0.10.0_f8f05c8ea/efficientnet_b0_warboy_2pe.enf.dvc
furiosa/models/data/generated/0.10.0_f8f05c8ea/efficientnet_v2_s_warboy_1pe.enf.dvc
furiosa/models/data/generated/0.10.0_f8f05c8ea/efficientnet_v2_s_warboy_2pe.enf.dvc
furiosa/models/data/generated/0.10.0_f8f05c8ea/mlcommons_resnet50_v1.5_warboy_1pe.enf.dvc
furiosa/models/data/generated/0.10.0_f8f05c8ea/mlcommons_resnet50_v1.5_warboy_2pe.enf.dvc
furiosa/models/data/generated/0.10.0_f8f05c8ea/mlcommons_ssd_mobilenet_v1_warboy_1pe.enf.dvc
furiosa/models/data/generated/0.10.0_f8f05c8ea/mlcommons_ssd_mobilenet_v1_warboy_2pe.enf.dvc
furiosa/models/data/generated/0.10.0_f8f05c8ea/mlcommons_ssd_resnet34_warboy_1pe.enf.dvc
furiosa/models/data/generated/0.10.0_f8f05c8ea/mlcommons_ssd_resnet34_warboy_2pe.enf.dvc
furiosa/models/data/generated/0.10.0_f8f05c8ea/yolov5l_warboy_1pe.enf.dvc
furiosa/models/data/generated/0.10.0_f8f05c8ea/yolov5l_warboy_2pe.enf.dvc
furiosa/models/data/generated/0.10.0_f8f05c8ea/yolov5m_warboy_1pe.enf.dvc
furiosa/models/data/generated/0.10.0_f8f05c8ea/yolov5m_warboy_2pe.enf.dvc
furiosa/models/data/generated/0.10.0_f8f05c8ea/yolov7_w6_pose_warboy_1pe.enf.dvc
furiosa/models/data/generated/0.10.0_f8f05c8ea/yolov7_w6_pose_warboy_2pe.enf.dvc
furiosa_models-0.10.2.dist-info/entry_points.txt
furiosa_models-0.10.2.dist-info/LICENSE
furiosa_models-0.10.2.dist-info/WHEEL
furiosa_models-0.10.2.dist-info/METADATA
furiosa_models-0.10.2.dist-info/RECORD
