Metadata-Version: 2.1
Name: furiosa-models
Version: 0.10.2
Summary: Furiosa Models
Author-email: "FurioaAI Inc." <pkg@furiosa.ai>
Requires-Python: ~=3.8
Classifier: Development Status :: 3 - Alpha
Classifier: Environment :: Console
Classifier: Intended Audience :: Developers
Classifier: Intended Audience :: System Administrators
Classifier: License :: OSI Approved :: Apache Software License
Classifier: Programming Language :: Python :: 3
Classifier: Programming Language :: Python :: 3.8
Classifier: Programming Language :: Python :: 3.9
Classifier: Programming Language :: Python :: 3.10
Classifier: Topic :: Software Development :: Libraries :: Python Modules
Classifier: Topic :: Scientific/Engineering :: Artificial Intelligence
Requires-Dist: furiosa-common == 0.10.*
Requires-Dist: furiosa-device == 0.10.*
Requires-Dist: furiosa-runtime == 0.10.*
Requires-Dist: furiosa-native-postprocess == 0.10.0
Requires-Dist: PyYAML
Requires-Dist: numpy
Requires-Dist: opencv-python-headless
Requires-Dist: pydantic ~= 2.0
Requires-Dist: requests
Requires-Dist: tabulate
Requires-Dist: torch
Requires-Dist: torchvision
Requires-Dist: typer
Requires-Dist: protobuf ~= 3.20
Requires-Dist: dvc[s3] ; extra == "dvc"
Requires-Dist: dvc[s3] ; extra == "full"
Requires-Dist: onnx ; extra == "full"
Requires-Dist: furiosa-serving == 0.10.* ; extra == "full"
Requires-Dist: furiosa-quantizer == 0.10.* ; extra == "full"
Requires-Dist: furiosa-serving == 0.10.* ; extra == "serving"
Requires-Dist: onnx ; extra == "test"
Requires-Dist: furiosa-serving == 0.10.* ; extra == "test"
Requires-Dist: furiosa-quantizer == 0.10.* ; extra == "test"
Requires-Dist: nbmake ; extra == "test"
Requires-Dist: pycocotools ~= 2.0.4 ; extra == "test"
Requires-Dist: pytest ; extra == "test"
Requires-Dist: pytest-asyncio ~= 0.17.2 ; extra == "test"
Requires-Dist: pytest-benchmark == 4.0.0 ; extra == "test"
Requires-Dist: torchvision ; extra == "test"
Project-URL: Bug Tracker, https://github.com/furiosa-ai/furiosa-models/issues
Project-URL: Documentation, https://furiosa-ai.github.io/furiosa-models/latest/
Project-URL: Home, https://furiosa.ai
Project-URL: Source Code, https://github.com/furiosa-ai/furiosa-models
Provides-Extra: dvc
Provides-Extra: full
Provides-Extra: serving
Provides-Extra: test
